{"v":"5.5.4","fr":24,"ip":0,"op":360,"w":1500,"h":1500,"nm":"合成 1","ddd":0,"assets":[{"id":"image_0","w":641,"h":371,"u":"images/","p":"img_0.png","e":0},{"id":"image_1","w":748,"h":319,"u":"images/","p":"img_1.png","e":0},{"id":"image_2","w":321,"h":199,"u":"images/","p":"img_2.png","e":0},{"id":"image_3","w":674,"h":379,"u":"images/","p":"img_3.png","e":0},{"id":"comp_0","layers":[{"ddd":0,"ind":1,"ty":0,"nm":"云朵B组循环","refId":"comp_1","sr":1,"ks":{"o":{"a":0,"k":100,"ix":11},"r":{"a":0,"k":0,"ix":10},"p":{"a":0,"k":[750,960,0],"ix":2},"a":{"a":0,"k":[750,960,0],"ix":1},"s":{"a":0,"k":[100,100,100],"ix":6}},"ao":0,"w":1500,"h":1920,"ip":0,"op":360,"st":0,"bm":0},{"ddd":0,"ind":2,"ty":0,"nm":"云朵A组 循环","refId":"comp_2","sr":1,"ks":{"o":{"a":0,"k":100,"ix":11},"r":{"a":0,"k":0,"ix":10},"p":{"a":0,"k":[750,960,0],"ix":2},"a":{"a":0,"k":[750,960,0],"ix":1},"s":{"a":0,"k":[100,100,100],"ix":6}},"ao":0,"w":1500,"h":1920,"ip":0,"op":360,"st":0,"bm":0}]},{"id":"comp_1","layers":[{"ddd":0,"ind":1,"ty":2,"nm":"云朵304_1.png","cl":"png","refId":"image_0","sr":1,"ks":{"o":{"a":1,"k":[{"i":{"x":[0.833],"y":[0.833]},"o":{"x":[0.167],"y":[0.167]},"t":0,"s":[0]},{"i":{"x":[0.833],"y":[0.833]},"o":{"x":[0.167],"y":[0.167]},"t":71,"s":[21.65]},{"i":{"x":[0.833],"y":[0.833]},"o":{"x":[0.167],"y":[0.167]},"t":132,"s":[100]},{"i":{"x":[0.833],"y":[0.833]},"o":{"x":[0.167],"y":[0.167]},"t":216,"s":[39]},{"t":317,"s":[0]}],"ix":11},"r":{"a":0,"k":0,"ix":10},"p":{"a":1,"k":[{"i":{"x":0.833,"y":0.833},"o":{"x":0.167,"y":0.167},"t":0,"s":[751,1013,0],"to":[7.208,6.125,0],"ti":[-4.556,-4.033,0]},{"i":{"x":0.833,"y":0.833},"o":{"x":0.167,"y":0.167},"t":132,"s":[841,1102,0],"to":[44.816,39.671,0],"ti":[-81.167,-90.333,0]},{"t":317,"s":[1328,1644,0]}],"ix":2},"a":{"a":0,"k":[320.5,185.5,0],"ix":1},"s":{"a":1,"k":[{"i":{"x":[0.833,0.833,0.833],"y":[0.833,0.833,0.833]},"o":{"x":[0.167,0.167,0.167],"y":[0.167,0.167,0.167]},"t":0,"s":[113,113,100]},{"i":{"x":[0.833,0.833,0.833],"y":[0.833,0.833,0.833]},"o":{"x":[0.167,0.167,0.167],"y":[0.167,0.167,0.167]},"t":132,"s":[200,200,100]},{"t":317,"s":[514,514,100]}],"ix":6}},"ao":0,"ip":0,"op":360,"st":0,"bm":0},{"ddd":0,"ind":2,"ty":2,"nm":"云朵303_1.png","cl":"png","refId":"image_1","sr":1,"ks":{"o":{"a":1,"k":[{"i":{"x":[0.833],"y":[0.833]},"o":{"x":[0.167],"y":[0.167]},"t":0,"s":[0]},{"i":{"x":[0.833],"y":[0.833]},"o":{"x":[0.167],"y":[0.167]},"t":71,"s":[17]},{"i":{"x":[0.833],"y":[0.833]},"o":{"x":[0.167],"y":[0.167]},"t":130,"s":[25]},{"i":{"x":[0.833],"y":[0.833]},"o":{"x":[0.167],"y":[0.167]},"t":167,"s":[63]},{"i":{"x":[0.833],"y":[0.833]},"o":{"x":[0.167],"y":[0.167]},"t":256,"s":[100]},{"t":314,"s":[0]}],"ix":11},"r":{"a":0,"k":0,"ix":10},"p":{"a":1,"k":[{"i":{"x":0.833,"y":0.833},"o":{"x":0.167,"y":0.167},"t":0,"s":[790,787,0],"to":[-9.584,11.713,0],"ti":[16.19,-24.577,0]},{"i":{"x":0.833,"y":0.833},"o":{"x":0.167,"y":0.167},"t":167,"s":[675.5,931.5,0],"to":[-46.799,71.042,0],"ti":[126.434,-189.797,0]},{"t":323,"s":[407,1330,0]}],"ix":2},"a":{"a":0,"k":[374,159.5,0],"ix":1},"s":{"a":1,"k":[{"i":{"x":[0.833,0.833,0.833],"y":[0.833,0.833,0.833]},"o":{"x":[0.167,0.167,0.167],"y":[0.167,0.167,0.167]},"t":0,"s":[83,83,100]},{"i":{"x":[0.833,0.833,0.833],"y":[0.833,0.833,0.833]},"o":{"x":[0.167,0.167,0.167],"y":[0.167,0.167,0.167]},"t":167,"s":[174,174,100]},{"t":323,"s":[482,482,100]}],"ix":6}},"ao":0,"ip":0,"op":360,"st":0,"bm":0},{"ddd":0,"ind":3,"ty":2,"nm":"云朵305_1.png","cl":"png","refId":"image_2","sr":1,"ks":{"o":{"a":1,"k":[{"i":{"x":[0.833],"y":[0.833]},"o":{"x":[0.167],"y":[0.167]},"t":0,"s":[0]},{"i":{"x":[0.833],"y":[0.833]},"o":{"x":[0.167],"y":[0.167]},"t":71,"s":[10.65]},{"i":{"x":[0.833],"y":[0.833]},"o":{"x":[0.167],"y":[0.167]},"t":178,"s":[100]},{"i":{"x":[0.833],"y":[0.833]},"o":{"x":[0.167],"y":[0.167]},"t":341,"s":[100]},{"t":359,"s":[1]}],"ix":11},"r":{"a":0,"k":0,"ix":10},"p":{"a":1,"k":[{"i":{"x":0.833,"y":0.833},"o":{"x":0.167,"y":0.167},"t":0,"s":[917,779,0],"to":[14.5,16.333,0],"ti":[-43,-51.333,0]},{"i":{"x":0.833,"y":0.833},"o":{"x":0.167,"y":0.167},"t":178,"s":[1004,877,0],"to":[43,51.333,0],"ti":[-28.5,-35,0]},{"t":359,"s":[1175,1087,0]}],"ix":2},"a":{"a":0,"k":[160.5,99.5,0],"ix":1},"s":{"a":1,"k":[{"i":{"x":[0.833,0.833,0.833],"y":[0.833,0.833,0.833]},"o":{"x":[0.167,0.167,0.167],"y":[0.167,0.167,0.167]},"t":0,"s":[110,110,100]},{"i":{"x":[0.833,0.833,0.833],"y":[0.833,0.833,0.833]},"o":{"x":[0.167,0.167,0.167],"y":[0.167,0.167,0.167]},"t":178,"s":[258,258,100]},{"t":359,"s":[593,593,100]}],"ix":6}},"ao":0,"ip":0,"op":360,"st":0,"bm":0}]},{"id":"comp_2","layers":[{"ddd":0,"ind":1,"ty":2,"nm":"云朵304_1.png","cl":"png","refId":"image_0","sr":1,"ks":{"o":{"a":1,"k":[{"i":{"x":[0.833],"y":[0.833]},"o":{"x":[0.167],"y":[0.167]},"t":0,"s":[100]},{"i":{"x":[0.833],"y":[0.833]},"o":{"x":[0.167],"y":[0.167]},"t":60,"s":[100]},{"i":{"x":[0.833],"y":[0.833]},"o":{"x":[0.167],"y":[0.167]},"t":128,"s":[47]},{"i":{"x":[0.833],"y":[0.833]},"o":{"x":[0.167],"y":[0.167]},"t":216,"s":[0]},{"i":{"x":[0.833],"y":[0.833]},"o":{"x":[0.167],"y":[0.167]},"t":290,"s":[100]},{"t":359,"s":[100]}],"ix":11},"r":{"a":0,"k":0,"ix":10},"p":{"a":1,"k":[{"i":{"x":0.833,"y":0.833},"o":{"x":0.167,"y":0.167},"t":0,"s":[730,1072.799,0],"to":[0,213.306,0],"ti":[0,-86.637,0]},{"i":{"x":0.833,"y":0.833},"o":{"x":0.167,"y":0.167},"t":215,"s":[730,1610,0],"to":[0,149.5,0],"ti":[0.638,-0.803,0]},{"i":{"x":0.833,"y":0.833},"o":{"x":0.167,"y":0.167},"t":216,"s":[730,1001.799,0],"to":[-1.47,1.85,0],"ti":[0,-0.273,0]},{"t":359,"s":[730,1072.799,0]}],"ix":2},"a":{"a":0,"k":[320.5,185.5,0],"ix":1},"s":{"a":1,"k":[{"i":{"x":[0.833,0.833,0.833],"y":[0.833,0.833,0.833]},"o":{"x":[0.167,0.167,0.167],"y":[0.167,0.167,0.167]},"t":0,"s":[195.826,195.826,100]},{"i":{"x":[0.833,0.833,0.833],"y":[0.833,0.833,0.833]},"o":{"x":[0.167,0.167,0.167],"y":[0.167,0.167,0.167]},"t":215,"s":[800,800,100]},{"i":{"x":[0.833,0.833,0.833],"y":[0.833,0.833,0.833]},"o":{"x":[0.167,0.167,0.167],"y":[0.167,0.167,0.167]},"t":216,"s":[85,85,100]},{"t":359,"s":[195.8,195.8,100]}],"ix":6}},"ao":0,"ip":0,"op":360,"st":0,"bm":0},{"ddd":0,"ind":2,"ty":2,"nm":"云朵303_1.png","cl":"png","refId":"image_1","sr":1,"ks":{"o":{"a":1,"k":[{"i":{"x":[0.833],"y":[0.833]},"o":{"x":[0.167],"y":[0.167]},"t":0,"s":[23]},{"i":{"x":[0.833],"y":[0.833]},"o":{"x":[0.167],"y":[0.167]},"t":90,"s":[52]},{"i":{"x":[0.833],"y":[0.833]},"o":{"x":[0.167],"y":[0.167]},"t":137,"s":[100]},{"i":{"x":[0.833],"y":[0.833]},"o":{"x":[0.167],"y":[0.167]},"t":190,"s":[0]},{"i":{"x":[0.833],"y":[0.833]},"o":{"x":[0.167],"y":[0.167]},"t":216,"s":[0]},{"i":{"x":[0.833],"y":[0.833]},"o":{"x":[0.167],"y":[0.167]},"t":290,"s":[21]},{"t":359,"s":[23]}],"ix":11},"r":{"a":0,"k":0,"ix":10},"p":{"a":1,"k":[{"i":{"x":0.833,"y":0.833},"o":{"x":0.167,"y":0.167},"t":0,"s":[621.086,1056.624,0],"to":[-24.256,218.537,0],"ti":[11.602,-89.762,0]},{"i":{"x":0.833,"y":0.833},"o":{"x":0.167,"y":0.167},"t":215,"s":[560,1506,0],"to":[-19.754,152.836,0],"ti":[0.273,-0.663,0]},{"i":{"x":0.833,"y":0.833},"o":{"x":0.167,"y":0.167},"t":216,"s":[627.086,991.624,0],"to":[-0.445,1.08,0],"ti":[-1.9,0.431,0]},{"t":359,"s":[621.086,1056.624,0]}],"ix":2},"a":{"a":0,"k":[374,159.5,0],"ix":1},"s":{"a":1,"k":[{"i":{"x":[0.833,0.833,0.833],"y":[0.833,0.833,0.833]},"o":{"x":[0.167,0.167,0.167],"y":[0.167,0.167,0.167]},"t":0,"s":[359.819,359.819,100]},{"i":{"x":[0.833,0.833,0.833],"y":[0.833,0.833,0.833]},"o":{"x":[0.167,0.167,0.167],"y":[0.167,0.167,0.167]},"t":215,"s":[800,800,100]},{"i":{"x":[0.833,0.833,0.833],"y":[0.833,0.833,0.833]},"o":{"x":[0.167,0.167,0.167],"y":[0.167,0.167,0.167]},"t":216,"s":[150,150,100]},{"t":359,"s":[359.819,359.819,100]}],"ix":6}},"ao":0,"ip":0,"op":360,"st":0,"bm":0},{"ddd":0,"ind":3,"ty":2,"nm":"云朵302_1.png","cl":"png","refId":"image_3","sr":1,"ks":{"o":{"a":1,"k":[{"i":{"x":[0.833],"y":[0.833]},"o":{"x":[0.167],"y":[0.167]},"t":0,"s":[100]},{"i":{"x":[0.833],"y":[0.833]},"o":{"x":[0.167],"y":[0.167]},"t":141,"s":[100]},{"i":{"x":[0.833],"y":[0.833]},"o":{"x":[0.167],"y":[0.167]},"t":244,"s":[0]},{"i":{"x":[0.833],"y":[0.833]},"o":{"x":[0.167],"y":[0.167]},"t":245,"s":[0]},{"i":{"x":[0.833],"y":[0.833]},"o":{"x":[0.167],"y":[0.167]},"t":324,"s":[82]},{"t":359,"s":[100]}],"ix":11},"r":{"a":0,"k":0,"ix":10},"p":{"a":1,"k":[{"i":{"x":0.833,"y":0.833},"o":{"x":0.167,"y":0.167},"t":0,"s":[210.418,1074.68,0],"to":[-192.565,136.427,0],"ti":[88.028,-45.912,0]},{"i":{"x":0.833,"y":0.833},"o":{"x":0.167,"y":0.167},"t":244,"s":[-908,1655,0],"to":[-367.167,191.5,0],"ti":[-0.134,1.046,0]},{"i":{"x":0.833,"y":0.833},"o":{"x":0.167,"y":0.167},"t":245,"s":[327.418,1012.68,0],"to":[0.156,-1.217,0],"ti":[-0.317,-0.197,0]},{"t":359,"s":[210.418,1074.68,0]}],"ix":2},"a":{"a":0,"k":[337,189.5,0],"ix":1},"s":{"a":1,"k":[{"i":{"x":[0.833,0.833,0.833],"y":[0.833,0.833,0.833]},"o":{"x":[0.167,0.167,0.167],"y":[0.167,0.167,0.167]},"t":0,"s":[195.132,195.132,100]},{"i":{"x":[0.833,0.833,0.833],"y":[0.833,0.833,0.833]},"o":{"x":[0.167,0.167,0.167],"y":[0.167,0.167,0.167]},"t":244,"s":[633,633,100]},{"i":{"x":[0.833,0.833,0.833],"y":[0.833,0.833,0.833]},"o":{"x":[0.167,0.167,0.167],"y":[0.167,0.167,0.167]},"t":245,"s":[50,50,100]},{"t":359,"s":[195.132,195.132,100]}],"ix":6}},"ao":0,"ip":0,"op":360,"st":0,"bm":0},{"ddd":0,"ind":4,"ty":2,"nm":"云朵305_1.png","cl":"png","refId":"image_2","sr":1,"ks":{"o":{"a":1,"k":[{"i":{"x":[0.833],"y":[0.833]},"o":{"x":[0.167],"y":[0.167]},"t":0,"s":[100]},{"i":{"x":[0.833],"y":[0.833]},"o":{"x":[0.167],"y":[0.167]},"t":120,"s":[100]},{"i":{"x":[0.833],"y":[0.833]},"o":{"x":[0.167],"y":[0.167]},"t":178,"s":[100]},{"i":{"x":[0.833],"y":[0.833]},"o":{"x":[0.167],"y":[0.167]},"t":215,"s":[4]},{"i":{"x":[0.833],"y":[0.833]},"o":{"x":[0.167],"y":[0.167]},"t":216,"s":[0]},{"i":{"x":[0.833],"y":[0.833]},"o":{"x":[0.167],"y":[0.167]},"t":306,"s":[23]},{"t":359,"s":[100]}],"ix":11},"r":{"a":0,"k":0,"ix":10},"p":{"a":1,"k":[{"i":{"x":0.833,"y":0.833},"o":{"x":0.167,"y":0.167},"t":0,"s":[1137.749,1030.797,0],"to":[31.99,10.401,0],"ti":[-65.079,-20.764,0]},{"i":{"x":0.833,"y":0.833},"o":{"x":0.167,"y":0.167},"t":215,"s":[1398,1110,0],"to":[10.777,3.438,0],"ti":[-12.148,-4.136,0]},{"i":{"x":0.833,"y":0.833},"o":{"x":0.167,"y":0.167},"t":216,"s":[1135.999,1030.297,0],"to":[0.389,0.132,0],"ti":[-76.366,-99.614,0]},{"t":359,"s":[1137.749,1030.797,0]}],"ix":2},"a":{"a":0,"k":[160.5,99.5,0],"ix":1},"s":{"a":1,"k":[{"i":{"x":[0.833,0.833,0.833],"y":[0.833,0.833,0.833]},"o":{"x":[0.167,0.167,0.167],"y":[0.167,0.167,0.167]},"t":0,"s":[436.003,436.003,100]},{"i":{"x":[0.833,0.833,0.833],"y":[0.833,0.833,0.833]},"o":{"x":[0.167,0.167,0.167],"y":[0.167,0.167,0.167]},"t":215,"s":[800,800,100]},{"i":{"x":[0.833,0.833,0.833],"y":[0.833,0.833,0.833]},"o":{"x":[0.167,0.167,0.167],"y":[0.167,0.167,0.167]},"t":216,"s":[235.003,235.003,100]},{"t":359,"s":[436.003,436.003,100]}],"ix":6}},"ao":0,"ip":0,"op":360,"st":0,"bm":0}]}],"layers":[{"ddd":0,"ind":4,"ty":0,"nm":"云朵动画效果","refId":"comp_0","sr":1,"ks":{"o":{"a":0,"k":55,"ix":11},"r":{"a":0,"k":0,"ix":10},"p":{"a":0,"k":[750,964,0],"ix":2},"a":{"a":0,"k":[750,960,0],"ix":1},"s":{"a":0,"k":[100,100,100],"ix":6}},"ao":0,"w":1500,"h":1920,"ip":0,"op":360,"st":0,"bm":0}],"markers":[]}